bmstu/__init__.py
bmstu/layers.py
bmstu/setup.py
bmstu/utls.py
bmstu/capsnet/__init__.py
bmstu/capsnet/em_utils.py
bmstu/capsnet/losses.py
bmstu/capsnet/models.py
bmstu/capsnet/utls.py
bmstu/capsnet/vos_utils.py
bmstu/capsnet/layers/__init__.py
bmstu/capsnet/layers/basic.py
bmstu/capsnet/layers/gamma.py
bmstu/capsnet/layers/matrix.py
bmstu/capsnet/layers/segment.py
bmstu/capsnet/layers/vos.py
bmstu/capsnet/metrics/__init__.py
bmstu/capsnet/metrics/gamma.py
bmstu/capsnet/metrics/matrix.py
bmstu/datasets/__init__.py
bmstu/datasets/ucf101.py
bmstu/datasets/ucf50.py
bmstu/datasets/utls.py
bmstu/dynamic_images/__init__.py
bmstu/dynamic_images/utls.py
tests/__init__.py
bmstu_ovchinnikov_capsnet-0.0.4a0.dist-info/METADATA
bmstu_ovchinnikov_capsnet-0.0.4a0.dist-info/WHEEL
bmstu_ovchinnikov_capsnet-0.0.4a0.dist-info/top_level.txt
bmstu_ovchinnikov_capsnet-0.0.4a0.dist-info/RECORD
